[
  {
    "start": "2016-03-07",
    "end": "2016-03-11",
    "department": "Musterabteilung",
    "work": [
      {
        "tasks": [
          "Musterarbeit",
          "Musterarbeit 2"
        ],
        "hours": [
          4,
          4
        ]
      },
      {
        "tasks": [
          "Musterarbeit"
        ],
        "hours": [
          8
        ]
      },
      {
        "tasks": [
          "Musterarbeit"
        ],
        "hours": [
          8
        ]
      },
      {
        "tasks": [
          "Musterarbeit"
        ],
        "hours": [
          8
        ]
      },
      {
        "tasks": [
          "Musterarbeit"
        ],
        "hours": [
          8
        ]
      }
    ]
  }
]